{ "device_family": "ns", "parent_name": "", "commands": [ { "protocol": "SSH", "parent_name": "configuration_template", "nitro_payload": "", "nitro_method": "", "parent_id": "47a0a397-6fa1-4284-9c5e-383bb07771e4", "index": "1", "timeout": "300", "id": "0ee9d168-62ab-484b-b09f-5441e50005fd", "nitro_resource": "", "command": "set HA Node -failsafe ON" }, { "protocol": "SSH", "parent_name": "configuration_template", "nitro_payload": "", "nitro_method": "", "parent_id": "47a0a397-6fa1-4284-9c5e-383bb07771e4", "index": "2", "timeout": "300", "id": "28f558dd-5d20-4fcc-bd3f-0c6edca68874", "nitro_resource": "", "command": "set hostname $hostname$" }, { "protocol": "SSH", "parent_name": "configuration_template", "nitro_payload": "", "nitro_method": "", "parent_id": "47a0a397-6fa1-4284-9c5e-383bb07771e4", "index": "3", "timeout": "300", "id": "b16140c9-1564-41b9-ac22-5c872399bf39", "nitro_resource": "", "command": "save config" }, { "protocol": "SSH", "parent_name": "configuration_template", "nitro_payload": "", "nitro_method": "", "parent_id": "47a0a397-6fa1-4284-9c5e-383bb07771e4", "index": "4", "timeout": "300", "id": "b687632c-bc8b-4285-b9a9-ed7580cab1db", "nitro_resource": "", "command": "force HA failover -force" } ], "name": "cj_baseline_node_b", "variables": [ { "parent_name": "configuration_template", "name": "hostname", "display_name": "hostname", "description": "", "parent_id": "47a0a397-6fa1-4284-9c5e-383bb07771e4", "required": "true", "default_value": "", "id": "4b71c289-c3bf-41a1-ae3e-041c2be27dc2", "type": "text_field", "values_enum_db": "", "values_enum": [ ] } ], "description": "cj_baseline_node_b", "parent_id": "", "is_visible": "true", "tenant_id": "1298c44c-da33-4d07-8216-2cd5c13c39e7", "id": "47a0a397-6fa1-4284-9c5e-383bb07771e4", "is_inbuilt": "false", "category": "" }